Workbook

Sheet Toelichting
A1: Maatschappelijke toets — AkzoNobel × Axalta (merger of equals, 2026)
A2: Geüpdatete maatschappelijke kosten-batenanalyse (MKBA). Illustratieve teaching-versie t.b.v. de masterclass.
A4: DOEL
A5: Het ESB-artikel 'Maatschappelijke toetsing van overnames is nodig' (Schoenmaker & De Groot Ruiz e.a., 2017) schatte de brede waarde (financieel + sociaal + milieu) van een AkzoNobel-overname door PPG: verwacht ca. –€6 mrd. Dit bestand past diezelfde methode toe op de situatie van 2026 — de fusie van gelijken met Axalta — en voegt, op verzoek, een vijfde effect toe: de impact op autonomie.
A7: METHODE
A8: Per effect schatten we een bandbreedte (onder / verwacht / boven), uitgedrukt in euro's (contante waarde, € mrd). Disconteringsvoet 3%; horizon 4 jaar (midden) en 8 jaar (extremen), net als in 2017. De post 'Werknemers' wordt gedreven door een expliciete banen-calculator (aantal banen × maatschappelijke waarde per baan × horizon). De totale toets is de som van de effecten (Rijnlands: T = F + S + M, alle stakeholders gelijk gewogen).
A10: SCOPE & COUNTERFACTUAL
A11: De toets vergelijkt 'fuseren met Axalta' met 'zelfstandig doorgaan'. Belangrijk: het afgewezen cash-bod van Nippon Paint + Sherwin-Williams (opsplitsing) is een dérde scenario dat op vrijwel elke post sléchter zou scoren (opsplitsing → meer banen- en autonomieverlies, sterkere consolidatie). Dat de fusie minder maatschappelijke schade geeft dan dat bod, ondersteunt feitelijk de keuze van het bestuur voor de MOE.
A13: WAAROM 2026 WEZENLIJK ANDERS IS DAN 2017 (PPG)
A14: • Fusie van gelijken (all-stock, geen premie), geen vijandige overname met opsplitsing.
A15: • Complementaire portefeuilles (Axalta: auto/refinish/mobility; AkzoNobel: deco/marine/powder) → minder directe marktoverlap dan PPG (een directe concurrent) → kleiner prijseffect, lagere mededingingsdrempel.
A16: • Geen erosie van een groot duurzaamheidsvoordeel zoals bij het minder-groene PPG; profielen zijn symmetrischer.
... A29: • Maatschappelijke waarde per baan (~€70.000/jaar): conform het ESB-artikel (2017).

Sheet MKBA 2026 MOE
A1: Maatschappelijke toets — AkzoNobel × Axalta (MOE), 2026
A2: Contante waarde in € mrd. Gele cellen = aanpasbare aannames. Methode naar ESB (2017).
A4: PARAMETERS (pas aan om scenario's te testen)
A5: Disconteringsvoet | B5: 0.03
A6: Horizon midden (jaren) | B6: 4
A7: Horizon extremen (jaren) | B7: 8
A8: Maatschappelijke waarde per baan (€/jaar) | B8: 70000
A9: Annuïteitsfactor — midden | B9: =(1-(1+B5)^-B6)/B5 -> 3.7170984
A10: Annuïteitsfactor — extremen | B10: =(1-(1+B5)^-B7)/B5 -> 7.0196922
A12: BANEN-CALCULATOR (drijft de post 'Werknemers')
A13: Scenario | B13: Netto banen (#) | C13: Horizon-factor | D13: Effect (€ mrd)
A14: Onder (meeste banenverlies) | B14: -5000 | C14: =B10 -> 7.0196922 | D14: =B14*$B$8*C14/1000000000 -> -2.4568923
A15: Verwacht | B15: -2000 | C15: =B9 -> 3.7170984 | D15: =B15*$B$8*C15/1000000000 -> -0.52039378
A16: Boven (beste) | B16: 500 | C16: =B10 -> 7.0196922 | D16: =B16*$B$8*C16/1000000000 -> 0.24568923
A18: MKBA — VIJF EFFECTEN (€ mrd, contante waarde)
A19: Effect | B19: Onder | C19: Verwacht | D19: Boven | E19: Belangrijkste aannames
A20: Werknemers | B20: =D14 -> -2.4568923 | C20: =D15 -> -0.52039378 | D20: =D16 -> 0.24568923 | E20: Synergie (~$600 mln) deels uit footprint/SG&A → banenverlies. Aanname: ~2.000 netto banen (verwacht), tot ~5.000 (onder). Combined headcount 46.551. MOE → minder dan bij vijandige overname (10–20% bij overgenomen partij).
A21: Consumenten (prijzen) | B21: -5 | C21: -1 | D21: 0 | E21: Complementaire portefeuilles → beperkte overlap; mededingingstoezicht remt prijseffect. Veel kleiner dan PPG (directe #1+#2). Aanname: prijsdruk op een kleine overlappende omzet, 0–2%.
A22: Klimaat (CO₂) | B22: -2 | C22: -0.3 | D22: 1 | E22: Geen groot duurzaamheidsvoordeel dat erodeert (anders dan AkzoNobel vs. minder-groen PPG). Symmetrische profielen; schaal kan groene R&D helpen (boven), integratie-afleiding kan schaden (onder). CO₂-prijs ~€110/ton.
A23: Aandeelhouders | B23: -2 | C23: 1.5 | D23: 4 | E23: ~$600 mln synergie gekapitaliseerd (~8×) ≈ €4–5 mrd bruto, minus integratiekosten en uitvoeringsrisico. Tegen: no-premium MOE en gemiste cash-premie (€73 vs ~€52); M&A-literatuur is sceptisch. €2,5 mrd superdividend = transfer.
A24: Autonomie (NL) | B24: -3 | C24: -1 | D24: -0.1 | E24: HQ deels naar Philadelphia, notering enkel NYSE (delisting Euronext), governance-gewicht verschuift. Mitigatie: NL-domicilie + 1 HQ Amsterdam + 55% behoud; basis al >60% VS. Bestuur framet het als méér strategische onafhankelijkheid → hardst te monetariseren post, deels kwalitatief.
A25: TOTAAL | B25: =SUM(B20:B24) -> -14.456892 | C25: =SUM(C20:C24) -> -1.3203938 | D25: =SUM(D20:D24) -> 5.1456892 | E25: Rijnlandse som T = F + S + M (alle stakeholders gelijk gewogen)
A27: Ter vergelijking: de PPG-overname (2017) had een verwacht totaal van ca. –€6 mrd (zelfde methode). Zie tab 'Vergelijking'.

Sheet Vergelijking
A1: PPG-overname (2017) vs. Axalta-fusie (2026) — € mrd
A3: Effect | B3: PPG 2017 — onder | C3: PPG 2017 — boven | D3: MOE 2026 — onder | E3: MOE 2026 — verwacht | F3: MOE 2026 — boven | G3: Waarom anders
A4: Werknemers | B4: -4.6 | C4: 1.5 | D4: ='MKBA 2026 MOE'!B20 -> -2.4568923 | E4: ='MKBA 2026 MOE'!C20 -> -0.52039378 | F4: ='MKBA 2026 MOE'!D20 -> 0.24568923 | G4: MOE i.p.v. opsplitsing → minder banenverlies; geen 10–20%-snit bij overgenomen partij.
A5: Consumenten (prijzen) | B5: -14.8 | C5: 0 | D5: ='MKBA 2026 MOE'!B21 -> -5 | E5: ='MKBA 2026 MOE'!C21 -> -1 | F5: ='MKBA 2026 MOE'!D21 -> 0 | G5: Complementair i.p.v. directe #1+#2 → veel kleiner prijseffect; mededingingstoezicht.
A6: Klimaat (CO₂) | B6: -7.2 | C6: 0.7 | D6: ='MKBA 2026 MOE'!B22 -> -2 | E6: ='MKBA 2026 MOE'!C22 -> -0.3 | F6: ='MKBA 2026 MOE'!D22 -> 1 | G6: Geen groot duurzaamheidsvoordeel dat verloren gaat; symmetrische profielen.
A7: Aandeelhouders | B7: -3.4 | C7: 3.2 | D7: ='MKBA 2026 MOE'!B23 -> -2 | E7: ='MKBA 2026 MOE'!C23 -> 1.5 | F7: ='MKBA 2026 MOE'!D23 -> 4 | G7: Concrete $600 mln synergie → eerder positief; maar no-premium en gemiste cash-premie.
A8: Autonomie (NL) | B8: n.v.t. | C8: – | D8: ='MKBA 2026 MOE'!B24 -> -3 | E8: ='MKBA 2026 MOE'!C24 -> -1 | F8: ='MKBA 2026 MOE'!D24 -> -0.1 | G8: NIEUW in 2026: HQ deels VS + enkel-NYSE. Mitigatie: NL-domicilie, 1 HQ, 55%, basis al >60% VS.
A9: TOTAAL | B9: -30 | C9: 5 | D9: ='MKBA 2026 MOE'!B25 -> -14.456892 | E9: ='MKBA 2026 MOE'!C25 -> -1.3203938 | F9: ='MKBA 2026 MOE'!D25 -> 5.1456892 | G9: PPG verwacht ≈ –€6 mrd; MOE verwacht ≈ licht negatief (≈ neutraal).
A11: Bron PPG-cijfers: Schoenmaker & De Groot Ruiz e.a., ESB 4752 (10 aug 2017), kader 1. MOE-cijfers: tab 'MKBA 2026 MOE'.
