Workbook

Sheet Overzicht
B2: Validatie — alle getallen uit de presentatie
B3: Eén tab per slide met getallen. Blauw = invoer (zoals op de slide). Zwart = herberekend met formule. Kolom ✓ = OK of CHECK.
B5: Slide | C5: Onderwerp | D5: Afwijkingen | E5: Status
B6: 08 | C6: W&V — voorbeeld | D6: =COUNTIF('Slide 08 - W&V vb'!D:D,"CHECK") -> 0 | E6: =IF(D6=0,"✓ alles klopt","⚠ "&D6&" afwijking(en) — zie tab") -> ✓ alles klopt
B7: 09 | C7: W&V — Alliander (2025/2024) | D7: =COUNTIF('Slide 09 - W&V Alliander'!D:D,"CHECK")+COUNTIF('Slide 09 - W&V Alliander'!G:G,"CHECK") -> 0 | E7: =IF(D7=0,"✓ alles klopt","⚠ "&D7&" afwijking(en) — zie tab") -> ✓ alles klopt
B8: 10 | C8: Balans — voorbeeld | D8: =COUNTIF('Slide 10 - Balans vb'!D:D,"CHECK") -> 0 | E8: =IF(D8=0,"✓ alles klopt","⚠ "&D8&" afwijking(en) — zie tab") -> ✓ alles klopt
B9: 11 | C9: Balans — Alliander (2025/2024) | D9: =COUNTIF('Slide 11 - Balans Alliander'!D:D,"CHECK")+COUNTIF('Slide 11 - Balans Alliander'!G:G,"CHECK") -> 0 | E9: =IF(D9=0,"✓ alles klopt","⚠ "&D9&" afwijking(en) — zie tab") -> ✓ alles klopt
B10: 12 | C10: Kasstroom — voorbeeld | D10: =COUNTIF('Slide 12 - Kasstroom vb'!D:D,"CHECK") -> 0 | E10: =IF(D10=0,"✓ alles klopt","⚠ "&D10&" afwijking(en) — zie tab") -> ✓ alles klopt
B11: 13 | C11: Kasstroom — Alliander (2025/2024) | D11: =COUNTIF('Slide 13 - Kasstr. Alliander'!D:D,"CHECK")+COUNTIF('Slide 13 - Kasstr. Alliander'!G:G,"CHECK") -> 0 | E11: =IF(D11=0,"✓ alles klopt","⚠ "&D11&" afwijking(en) — zie tab") -> ✓ alles klopt
B12: 14 | C12: Kerngetallen & ratio's — voorbeeld | D12: =COUNTIF('Slide 14 - Kerngetallen vb'!D:D,"CHECK") -> 0 | E12: =IF(D12=0,"✓ alles klopt","⚠ "&D12&" afwijking(en) — zie tab") -> ✓ alles klopt
B13: 15 | C13: Kerngetallen & ratio's — Alliander | D13: =COUNTIF('Slide 15 - Kerngetallen All'!D:D,"CHECK") -> 0 | E13: =IF(D13=0,"✓ alles klopt","⚠ "&D13&" afwijking(en) — zie tab") -> ✓ alles klopt
B14: 16 | C14: Waarde — AkzoNobel FY2025 | D14: =COUNTIF('Slide 16 - AkzoNobel waarde'!D:D,"CHECK") -> 0 | E14: =IF(D14=0,"✓ alles klopt","⚠ "&D14&" afwijking(en) — zie tab") -> ✓ alles klopt
B15: 17 | C15: Markt- vs fundamentele waarde | D15: =COUNTIF('Slide 17 - Markt vs fund.'!D:D,"CHECK") -> 0 | E15: =IF(D15=0,"✓ alles klopt","⚠ "&D15&" afwijking(en) — zie tab") -> ✓ alles klopt
B16: 18-19 | C16: Referentiegetallen (synergie, €6 mrd) | D16: — | E16: invoer/totalen (geen afleiding)
B17: 21 | C17: IP&L — Alliander (6 kapitalen) | D17: — | E17: invoer/totalen (geen afleiding)
C19: Totaal afwijkingen | D19: =SUM(D6:D17) -> 0 | E19: =IF(D19=0,"✓ presentatie volledig consistent","⚠ controleer gemarkeerde tabs") -> ✓ presentatie volledig consistent

Sheet Slide 08 - W&V vb
A1: Regel | B1: Op slide | C1: Herberekend | D1: ✓ | E1: Toelichting
A2: Omzet | B2: 150
A3: Operationele kosten | B3: -135
A4: EBITDA | B4: 15 | C4: =B2+B3 -> 15 | D4: =IF(ABS(B4-C4)<=0.5,"OK","CHECK") -> OK | E4: → omzet + operationele kosten
A5: Afschrijvingen | B5: -4
A6: EBIT (bedrijfsresultaat) | B6: 11 | C6: =B4+B5 -> 11 | D6: =IF(ABS(B6-C6)<=0.5,"OK","CHECK") -> OK | E6: → EBITDA + afschrijvingen
A7: Rente + belasting | B7: -3.5
A8: Nettowinst | B8: 7.5 | C8: =B6+B7 -> 7.5 | D8: =IF(ABS(B8-C8)<=0.5,"OK","CHECK") -> OK | E8: → EBIT + rente en belasting

Sheet Slide 10 - Balans vb
A1: Regel | B1: Op slide | C1: Herberekend | D1: ✓ | E1: Toelichting
A2: ACTIVA (€ mln)
A3: Vaste activa | B3: 50 | C3: =B4+B5 -> 50 | D3: =IF(ABS(B3-C3)<=0.5,"OK","CHECK") -> OK | E3: → MVA + IVA
A4: Materiële vaste activa | B4: 45
A5: Immateriële vaste activa | B5: 5
A6: Vlottende activa | B6: 70 | C6: =B7+B8+B9 -> 70 | D6: =IF(ABS(B6-C6)<=0.5,"OK","CHECK") -> OK | E6: → voorraad + debiteuren + liquide
A7: Voorraad | B7: 30
A8: Debiteuren | B8: 15
A9: Liquide middelen | B9: 25
A10: Totaal activa | B10: 120 | C10: =B3+B6 -> 120 | D10: =IF(ABS(B10-C10)<=0.5,"OK","CHECK") -> OK | E10: → vaste + vlottende activa
A11: PASSIVA (€ mln)
A12: Eigen vermogen | B12: 55
A13: Langlopende schulden | B13: 35 | C13: =B14 -> 35 | D13: =IF(ABS(B13-C13)<=0.5,"OK","CHECK") -> OK | E13: → banklening
A14: Banklening | B14: 35
A15: Kortlopende schulden | B15: 30 | C15: =B16+B17 -> 30 | D15: =IF(ABS(B15-C15)<=0.5,"OK","CHECK") -> OK | E15: → crediteuren + overige
A16: Crediteuren | B16: 25
A17: Overige | B17: 5
A18: Totaal passiva | B18: 120 | C18: =B12+B13+B15 -> 120 | D18: =IF(ABS(B18-C18)<=0.5,"OK","CHECK") -> OK | E18: → EV + langlopend + kortlopend
A19: Balans sluit (activa = passiva)? | B19: 0 | C19: =B10-B18 -> 0 | D19: =IF(ABS(B19-C19)<=0.5,"OK","CHECK") -> OK | E19: verschil moet 0 zijn
A20: Buffer = solvabiliteit (EV/balans) | B20: 0.46 | C20: =B12/B10 -> 0.45833333 | D20: =IF(ABS(B20-C20)<=0.005,"OK","CHECK") -> OK | E20: 45,8% ≈ 46% op slide

Sheet Slide 12 - Kasstroom vb
A1: Regel | B1: Op slide | C1: Herberekend | D1: ✓ | E1: Toelichting
A2: Nettowinst | B2: 7.5
A3: + Afschrijvingen | B3: 4
A4: - Mutatie werkkapitaal | B4: -5.5
A5: Operationele kasstroom | B5: 6 | C5: =B2+B3+B4 -> 6 | D5: =IF(ABS(B5-C5)<=0.5,"OK","CHECK") -> OK | E5: → winst + afschr − werkkapitaal
A6: Investeringen | B6: -7
A7: Kasstroom investeringen | B7: -7 | C7: =B6 -> -7 | D7: =IF(ABS(B7-C7)<=0.5,"OK","CHECK") -> OK | E7: → investeringen
A8: Opgenomen lening | B8: 3
A9: Betaald dividend | B9: -1
A10: Kasstroom financiering | B10: 2 | C10: =B8+B9 -> 2 | D10: =IF(ABS(B10-C10)<=0.5,"OK","CHECK") -> OK | E10: → lening − dividend
A11: Netto kasmutatie | B11: 1 | C11: =B5+B7+B10 -> 1 | D11: =IF(ABS(B11-C11)<=0.5,"OK","CHECK") -> OK | E11: → operationeel + investeren + financieren

Sheet Slide 09 - W&V Alliander
A1: Regel | B1: 2025 op slide | C1: 2025 herber. | D1: ✓ '25 | E1: 2024 op slide | F1: 2024 herber. | G1: ✓ '24 | H1: Toelichting
A2: Netto-omzet | B2: 3273 | E2: 3043
A3: Overige baten (incl. desinvest.) | B3: 124 | E3: 838 | H3: 2024 incl. €757 mln boekwinst Kenter
A4: Totaal bedrijfsopbrengsten | B4: 3397 | C4: =B2+B3 -> 3397 | D4: =IF(ABS(B4-C4)<=0.5,"OK","CHECK") -> OK | E4: 3881 | F4: =E2+E3 -> 3881 | G4: =IF(ABS(E4-F4)<=0.5,"OK","CHECK") -> OK | H4: → netto-omzet + overige baten
A5: Bedrijfskosten excl. afschr. | B5: -2328 | E5: -2207
A6: Afschrijvingen | B6: -596 | E6: -565
A7: EBITDA | B7: 1069 | C7: =B4+B5 -> 1069 | D7: =IF(ABS(B7-C7)<=0.5,"OK","CHECK") -> OK | E7: 1674 | F7: =E4+E5 -> 1674 | G7: =IF(ABS(E7-F7)<=0.5,"OK","CHECK") -> OK | H7: → bedrijfsopbrengsten + bedrijfskosten
A8: Bedrijfsresultaat (EBIT) | B8: 473 | C8: =B7+B6 -> 473 | D8: =IF(ABS(B8-C8)<=0.5,"OK","CHECK") -> OK | E8: 1109 | F8: =E7+E6 -> 1109 | G8: =IF(ABS(E8-F8)<=0.5,"OK","CHECK") -> OK | H8: → EBITDA + afschrijvingen
A9: Financieel, belasting & overig | B9: -184 | E9: -133
A10: Nettoresultaat | B10: 289 | C10: =B8+B9 -> 289 | D10: =IF(ABS(B10-C10)<=0.5,"OK","CHECK") -> OK | E10: 976 | F10: =E8+E9 -> 976 | G10: =IF(ABS(E10-F10)<=0.5,"OK","CHECK") -> OK | H10: → EBIT + financieel/belasting

Sheet Slide 11 - Balans Alliander
A1: Regel | B1: 2025 op slide | C1: 2025 herber. | D1: ✓ '25 | E1: 2024 op slide | F1: 2024 herber. | G1: ✓ '24 | H1: Toelichting
A2: Materiële vaste activa (het net) | B2: 12547 | E2: 11195
A3: Overige vaste activa | B3: 587 | E3: 524
A4: Totaal vaste activa | B4: 13134 | C4: =B2+B3 -> 13134 | D4: =IF(ABS(B4-C4)<=0.5,"OK","CHECK") -> OK | E4: 11719 | F4: =E2+E3 -> 11719 | G4: =IF(ABS(E4-F4)<=0.5,"OK","CHECK") -> OK | H4: → MVA + overige vaste activa
A5: Vlottende activa | B5: 1029 | E5: 1237 | H5: zie controle bij totaal activa 2024
A6: Totaal activa | B6: 14163 | C6: =B4+B5 -> 14163 | D6: =IF(ABS(B6-C6)<=0.5,"OK","CHECK") -> OK | E6: 12956 | F6: =E4+E5 -> 12956 | G6: =IF(ABS(E6-F6)<=0.5,"OK","CHECK") -> OK | H6: → vaste + vlottende activa
A7: Eigen vermogen * | B7: 6203 | E7: 6038 | H7: * incl. ~€1,0 mrd eeuwigdurende obligaties
A8: Langlopende schuld | B8: 4568 | E8: 3872
A9: Vooruitontvangen opbrengsten | B9: 2092 | E9: 2050
A10: Overige verplichtingen | B10: 1300 | E10: 996
A11: Totaal passiva | B11: 14163 | C11: =B7+B8+B9+B10 -> 14163 | D11: =IF(ABS(B11-C11)<=0.5,"OK","CHECK") -> OK | E11: 12956 | F11: =E7+E8+E9+E10 -> 12956 | G11: =IF(ABS(E11-F11)<=0.5,"OK","CHECK") -> OK | H11: → EV + schulden + verplichtingen
A12: Balans sluit (activa = passiva)? | B12: 0 | C12: =B6-B11 -> 0 | D12: =IF(ABS(B12-C12)<=0.5,"OK","CHECK") -> OK | E12: 0 | F12: =E6-E11 -> 0 | G12: =IF(ABS(E12-F12)<=0.5,"OK","CHECK") -> OK | H12: verschil moet 0 zijn
A13: Solvabiliteit (EV / balanstotaal) | B13: 0.438 | C13: =B7/B6 -> 0.43797218 | D13: =IF(ABS(B13-C13)<=0.001,"OK","CHECK") -> OK | E13: 0.466 | F13: =E7/E6 -> 0.4660389 | G13: =IF(ABS(E13-F13)<=0.001,"OK","CHECK") -> OK | H13: 43,8% ≈ 44% op slide (2025)

Sheet Slide 13 - Kasstr. Alliander
A1: Regel | B1: 2025 op slide | C1: 2025 herber. | D1: ✓ '25 | E1: 2024 op slide | F1: 2024 herber. | G1: ✓ '24 | H1: Toelichting
A2: Operationele activiteiten | B2: 832 | E2: 829
A3: Investeringen materiële activa | B3: -2071 | E3: -1772
A4: Overige investeringen (netto) | B4: 221 | E4: 1093 | H4: 2024 hoog: Kenter-opbrengst €919 mln
A5: Kasstroom investeringsactiviteiten | B5: -1850 | C5: =B3+B4 -> -1850 | D5: =IF(ABS(B5-C5)<=0.5,"OK","CHECK") -> OK | E5: -679 | F5: =E3+E4 -> -679 | G5: =IF(ABS(E5-F5)<=0.5,"OK","CHECK") -> OK | H5: → investeringen + overige
A6: Kasstroom financieringsactiviteiten | B6: 829 | E6: 102 | H6: 2025: groene obligatie €992 mln
A7: Nettokasstroom | B7: -189 | C7: =B2+B5+B6 -> -189 | D7: =IF(ABS(B7-C7)<=0.5,"OK","CHECK") -> OK | E7: 252 | F7: =E2+E5+E6 -> 252 | G7: =IF(ABS(E7-F7)<=0.5,"OK","CHECK") -> OK | H7: → operationeel + investeren + financieren
A8: Liquide middelen 31 dec. | B8: 307 | E8: 496 | H8: saldo (vereist beginstand voor afleiding)

Sheet Slide 14 - Kerngetallen vb
A1: Regel | B1: Op slide | C1: Herberekend | D1: ✓ | E1: Toelichting
A2: KERNGETALLEN (€ mln)
A3: Omzet | B3: 150 | C3: ='Slide 08 - W&V vb'!B2 -> 150 | D3: =IF(ABS(B3-C3)<=0.5,"OK","CHECK") -> OK | E3: bron: W&V (slide 8)
A4: EBITDA | B4: 15 | C4: ='Slide 08 - W&V vb'!B4 -> 15 | D4: =IF(ABS(B4-C4)<=0.5,"OK","CHECK") -> OK | E4: bron: W&V (slide 8)
A5: Opex (operationele kosten) | B5: 135 | C5: =-'Slide 08 - W&V vb'!B3 -> 135 | D5: =IF(ABS(B5-C5)<=0.5,"OK","CHECK") -> OK | E5: → |operationele kosten| (slide 8)
A6: Capex (investeringen) | B6: 7 | C6: =-'Slide 12 - Kasstroom vb'!B6 -> 7 | D6: =IF(ABS(B6-C6)<=0.5,"OK","CHECK") -> OK | E6: → |investeringen| (slide 12)
A7: Nettoresultaat | B7: 7.5 | C7: ='Slide 08 - W&V vb'!B8 -> 7.5 | D7: =IF(ABS(B7-C7)<=0.5,"OK","CHECK") -> OK | E7: bron: W&V (slide 8)
A8: Liquide middelen | B8: 25 | C8: ='Slide 10 - Balans vb'!B9 -> 25 | D8: =IF(ABS(B8-C8)<=0.5,"OK","CHECK") -> OK | E8: bron: balans (slide 10)
A9: Eigen vermogen | B9: 55 | C9: ='Slide 10 - Balans vb'!B12 -> 55 | D9: =IF(ABS(B9-C9)<=0.5,"OK","CHECK") -> OK | E9: bron: balans (slide 10)
A10: Vreemd vermogen | B10: 65 | C10: ='Slide 10 - Balans vb'!B10-'Slide 10 - Balans vb'!B12 -> 65 | D10: =IF(ABS(B10-C10)<=0.5,"OK","CHECK") -> OK | E10: → balanstotaal − EV
A11: Balanstotaal | B11: 120 | C11: ='Slide 10 - Balans vb'!B10 -> 120 | D11: =IF(ABS(B11-C11)<=0.5,"OK","CHECK") -> OK | E11: bron: balans (slide 10)
A12: KERNRATIO'S
A13: EBITDA-marge (EBITDA/omzet) | B13: 0.1 | C13: =B4/B3 -> 0.1 | D13: =IF(ABS(B13-C13)<=0.005,"OK","CHECK") -> OK | E13: 15 / 150 = 10%
A14: Nettomarge (resultaat/omzet) | B14: 0.05 | C14: =B7/B3 -> 0.05 | D14: =IF(ABS(B14-C14)<=0.005,"OK","CHECK") -> OK | E14: 7,5 / 150 = 5%
A15: Solvabiliteit (EV/balanstotaal) | B15: 0.46 | C15: =B9/B11 -> 0.45833333 | D15: =IF(ABS(B15-C15)<=0.005,"OK","CHECK") -> OK | E15: 55 / 120 = 45,8% ≈ 46%
A16: Net debt / EBITDA | B16: 0.7 | C16: =('Slide 10 - Balans vb'!B14-B8)/B4 -> 0.66666667 | D16: =IF(ABS(B16-C16)<=0.05,"OK","CHECK") -> OK | E16: (banklening 35 − liquide 25)/15 = 0,67
A17: Current ratio (vlottend/kortlopend) | B17: 2.3 | C17: ='Slide 10 - Balans vb'!B6/'Slide 10 - Balans vb'!B15 -> 2.3333333 | D17: =IF(ABS(B17-C17)<=0.05,"OK","CHECK") -> OK | E17: 70 / 30 = 2,33

Sheet Slide 15 - Kerngetallen All
A1: Regel | B1: Op slide | C1: Herberekend | D1: ✓ | E1: Toelichting
A2: KERNGETALLEN (€ mln) — 2025
A3: Omzet | B3: 3273 | C3: ='Slide 09 - W&V Alliander'!B2 -> 3273 | D3: =IF(ABS(B3-C3)<=0.5,"OK","CHECK") -> OK | E3: bron: W&V (slide 9)
A4: EBITDA | B4: 1069 | C4: ='Slide 09 - W&V Alliander'!B7 -> 1069 | D4: =IF(ABS(B4-C4)<=0.5,"OK","CHECK") -> OK | E4: bron: W&V (slide 9)
A5: Opex (operationele kosten) | B5: 2328 | C5: =-'Slide 09 - W&V Alliander'!B5 -> 2328 | D5: =IF(ABS(B5-C5)<=0.5,"OK","CHECK") -> OK | E5: → |bedrijfskosten| (slide 9)
A6: Capex (investeringen) | B6: 2071 | C6: =-'Slide 13 - Kasstr. Alliander'!B3 -> 2071 | D6: =IF(ABS(B6-C6)<=0.5,"OK","CHECK") -> OK | E6: → |investeringen mat. activa| (slide 13)
A7: Nettoresultaat | B7: 289 | C7: ='Slide 09 - W&V Alliander'!B10 -> 289 | D7: =IF(ABS(B7-C7)<=0.5,"OK","CHECK") -> OK | E7: bron: W&V (slide 9)
A8: Liquide middelen | B8: 307 | C8: ='Slide 13 - Kasstr. Alliander'!B8 -> 307 | D8: =IF(ABS(B8-C8)<=0.5,"OK","CHECK") -> OK | E8: bron: kasstroom (slide 13)
A9: Eigen vermogen | B9: 6203 | C9: ='Slide 11 - Balans Alliander'!B7 -> 6203 | D9: =IF(ABS(B9-C9)<=0.5,"OK","CHECK") -> OK | E9: bron: balans (slide 11)
A10: Vreemd vermogen | B10: 7960 | C10: ='Slide 11 - Balans Alliander'!B6-'Slide 11 - Balans Alliander'!B7 -> 7960 | D10: =IF(ABS(B10-C10)<=0.5,"OK","CHECK") -> OK | E10: → balanstotaal − EV
A11: Balanstotaal | B11: 14163 | C11: ='Slide 11 - Balans Alliander'!B6 -> 14163 | D11: =IF(ABS(B11-C11)<=0.5,"OK","CHECK") -> OK | E11: bron: balans (slide 11)
A12: KERNRATIO'S — 2025
A13: EBITDA-marge | B13: 0.327 | C13: =B4/B3 -> 0.32661167 | D13: =IF(ABS(B13-C13)<=0.0006,"OK","CHECK") -> OK | E13: 1.069 / 3.273 = 32,7%
A14: Nettomarge | B14: 0.088 | C14: =B7/B3 -> 0.088298197 | D14: =IF(ABS(B14-C14)<=0.0006,"OK","CHECK") -> OK | E14: 289 / 3.273 = 8,8%
A15: Solvabiliteit | B15: 0.44 | C15: =B9/B11 -> 0.43797218 | D15: =IF(ABS(B15-C15)<=0.005,"OK","CHECK") -> OK | E15: 6.203 / 14.163 = 43,8% ≈ 44%
A16: Net debt / EBITDA (~4) | B16: 4 | C16: =('Slide 11 - Balans Alliander'!B8-B8)/B4 -> 3.9859682 | D16: =IF(ABS(B16-C16)<=0.5,"OK","CHECK") -> OK | E16: (langlopende schuld 4.568 − liquide 307)/1.069 ≈ 4

Sheet Slide 16 - AkzoNobel waarde
A1: Regel | B1: Op slide | C1: Herberekend | D1: ✓ | E1: Toelichting
A2: Omzet (~€10,2 mrd) | B2: 10200 | E2: FY2025, ~ afgerond
A3: Adj. EBITDA | B3: 1444 | E3: FY2025 (€ mln)
A4: Nettowinst | B4: 635 | E4: FY2025 (€ mln)
A5: Adj. EBITDA-marge (afgeleid) | B5: 0.142 | C5: =B3/B2 -> 0.14156863 | D5: =IF(ABS(B5-C5)<=0.003,"OK","CHECK") -> OK | E5: 1.444 / 10.200 ≈ 14,2%
A6: Gecombineerde EV (~$25 mrd) | B6: 25000 | E6: indicatief, fusie ($ mln)

Sheet Slide 17 - Markt vs fund.
A1: Regel | B1: Op slide | C1: Herberekend | D1: ✓ | E1: Toelichting
A2: Beurskoers (~€52) | B2: 52 | E2: indicatief, per aandeel
A3: Cash-bod | B3: 73 | E3: per aandeel — afgewezen
A4: Premie bod t.o.v. koers (afgeleid) | B4: 0.404 | C4: =(B3-B2)/B2 -> 0.40384615 | D4: =IF(ABS(B4-C4)<=0.01,"OK","CHECK") -> OK | E4: (73 − 52)/52 ≈ 40%

Sheet Slide 18-19 - Referentie
A1: Regel | B1: Op slide | C1: Herberekend | D1: ✓ | E1: Toelichting
A2: Slide 18 — synergie (~$600 mln/jaar) | B2: 600 | E2: verwachte jaarlijkse synergie (casus)
A3: Slide 19 — maatsch. waardeverlies opsplitsing (~€6 mrd) | B3: 6000 | E3: Schoenmaker & De Groot Ruiz, bod 2017 (€ mln)

Sheet Slide 21 - IP&L Alliander
A1: Kapitaal | B1: Positief (+) | C1: Negatief (−) | D1: Toelichting
A2: Financieel · resultaat | B2: 289 | D2: Nettoresultaat 2025
A3: Geproduceerd · energietransport → welzijn | B3: 5814 | C3: 2437 | D3: Baten elektr/gas/zakelijk/zon; lasten inkoop
A4: Intellectueel · data & marktfacilitering | B4: 1
A5: Menselijk · welzijn werk vs. arbeid | B5: 115 | C5: 92 | D5: Arbeid + veiligheid
A6: Sociaal · cohesie (n.g.) vs. privacy | C6: 4 | D6: cohesie niet gekwantificeerd
A7: Natuurlijk · klimaat, materialen, afval | C7: 294 | D7: CO₂ 265 + materialen 27 + afval/biodiv 2
A8: Totaal positief | B8: =SUM(B2:B7) -> 6219 | D8: som van alle positieve posten
A9: Totaal negatief | C9: =SUM(C2:C7) -> 2827 | D9: som van alle negatieve posten
A10: Netto integrale bijdrage | B10: =B8-C9 -> 3392 | D10: =IF(B10>0,"OK — sterk positief (claim klopt)","CHECK") -> OK — sterk positief (claim klopt)
